README.txt
setup.cfg
setup.py
Products/__init__.py
Products.QuillsRemoteBlogging.egg-info/PKG-INFO
Products.QuillsRemoteBlogging.egg-info/SOURCES.txt
Products.QuillsRemoteBlogging.egg-info/dependency_links.txt
Products.QuillsRemoteBlogging.egg-info/entry_points.txt
Products.QuillsRemoteBlogging.egg-info/namespace_packages.txt
Products.QuillsRemoteBlogging.egg-info/not-zip-safe
Products.QuillsRemoteBlogging.egg-info/requires.txt
Products.QuillsRemoteBlogging.egg-info/top_level.txt
Products/QuillsRemoteBlogging/LICENSE.txt
Products/QuillsRemoteBlogging/README.txt
Products/QuillsRemoteBlogging/__init__.py
Products/QuillsRemoteBlogging/config.py
Products/QuillsRemoteBlogging/configure.zcml
Products/QuillsRemoteBlogging/uidmanager.py
Products/QuillsRemoteBlogging/usermanager.py
Products/QuillsRemoteBlogging/Extensions/Install.py
Products/QuillsRemoteBlogging/tests/__init__.py
Products/QuillsRemoteBlogging/tests/base.py
Products/QuillsRemoteBlogging/tests/test_docfile.py
Products/QuillsRemoteBlogging/tests/test_doctests.py
docs/HISTORY.txt
docs/INSTALL.txt
docs/LICENSE.GPL
docs/LICENSE.txt
